datagym/__init__.py
datagym/client.py
datagym/constants.py
datagym/endpoints.py
datagym/exceptions/__init__.py
datagym/exceptions/en.json
datagym/exceptions/exceptions.py
datagym/importers/__init__.py
datagym/importers/coco.py
datagym/models/__init__.py
datagym/models/dataset.py
datagym/models/image.py
datagym/models/label_config.py
datagym/models/project.py
datagym/models/video.py
datagym/utils/__init__.py
datagym/utils/coco_utils.py
datagym/utils/loadingbar.py
datagym-0.7.2.dist-info/LICENSE
datagym-0.7.2.dist-info/METADATA
datagym-0.7.2.dist-info/WHEEL
datagym-0.7.2.dist-info/top_level.txt
datagym-0.7.2.dist-info/RECORD
