Metadata-Version: 2.1
Name: datagym
Version: 0.7.2
Summary: Datagym Python API Wrapper
Home-page: https://www.datagym.ai/
Author: Johannes Pflugmacher, Alexej Penner, Bartu Soykök
Author-email: support@datagym.ai
License: BSD license
Platform: UNKNOWN
Classifier: Development Status :: 3 - Alpha
Classifier: Intended Audience :: Developers
Classifier: Intended Audience :: Science/Research
Classifier: License :: OSI Approved :: BSD License
Classifier: Natural Language :: English
Classifier: Programming Language :: Python :: 3
Classifier: Programming Language :: Python :: 3.6
Classifier: Programming Language :: Python :: 3.7
Classifier: Programming Language :: Python :: 3.8
Requires-Python: >=3.6
Requires-Dist: ndg-httpsclient (==0.5.1)
Requires-Dist: numpy (==1.22.2)
Requires-Dist: opencv-python (==4.5.5.62)
Requires-Dist: pyasn1 (==0.4.8)
Requires-Dist: pyopenssl (==19.1.0)
Requires-Dist: requests[security] (==2.22.0)
